[{"voiceQuality":5,"audioIssues":["CALL_PERFECT"],"environment":"INDOOR","comment":null,"carrier":"AIRTEL","networkGeneration":"WiFi","signalStrength":null,"latitude":null,"longitude":null,"timestamp":1775407362840,"callDuration":286200,"id":"69d29108f3d7b3dad8c014ff","created_at":"2026-04-05T16:42:48.253000"},{"voiceQuality":5,"audioIssues":["CALL_PERFECT"],"environment":"INDOOR","comment":null,"carrier":"AIRTEL","networkGeneration":"LTE","signalStrength":null,"latitude":null,"longitude":null,"timestamp":1775406946639,"callDuration":476446,"id":"69d28f68f3d7b3dad8c014fe","created_at":"2026-04-05T16:35:52.066000"},{"voiceQuality":5,"audioIssues":["CALL_PERFECT"],"environment":"OUTDOOR","comment":null,"carrier":"AIRTEL","networkGeneration":"WiFi","signalStrength":null,"latitude":null,"longitude":null,"timestamp":1775396155173,"callDuration":87835,"id":"69d26542f3d7b3dad8c014fd","created_at":"2026-04-05T13:36:02.066000"},{"voiceQuality":3,"audioIssues":["COULD_NOT_HEAR_OTHER"],"environment":"INDOOR","comment":null,"carrier":"AIRTEL","networkGeneration":"WiFi","signalStrength":null,"latitude":null,"longitude":null,"timestamp":1775321051910,"callDuration":121271,"id":"69d13fe7f3d7b3dad8c014fc","created_at":"2026-04-04T16:44:23.783000"},{"voiceQuality":5,"audioIssues":["CALL_PERFECT"],"environment":"INDOOR","comment":null,"carrier":"AIRTEL","networkGeneration":"WiFi","signalStrength":null,"latitude":null,"longitude":null,"timestamp":1775301539748,"callDuration":159554,"id":"69d0f3a9f3d7b3dad8c014fb","created_at":"2026-04-04T11:19:05.058000"},{"voiceQuality":3,"audioIssues":["OTHER_COULD_NOT_HEAR_ME"],"environment":"OUTDOOR","comment":null,"carrier":"AIRTEL","networkGeneration":"LTE","signalStrength":null,"latitude":null,"longitude":null,"timestamp":1775300807344,"callDuration":109103,"id":"69d0f0d2f3d7b3dad8c014fa","created_at":"2026-04-04T11:06:58.941000"},{"voiceQuality":null,"audioIssues":null,"environment":null,"comment":null,"carrier":"AIRTEL","networkGeneration":"LTE","signalStrength":null,"latitude":null,"longitude":null,"timestamp":1775298557025,"callDuration":32490,"id":"69d0e7fff3d7b3dad8c014f9","created_at":"2026-04-04T10:29:19.874000"},{"voiceQuality":5,"audioIssues":["CALL_PERFECT"],"environment":"INDOOR","comment":null,"carrier":"AIRTEL","networkGeneration":"WiFi","signalStrength":null,"latitude":null,"longitude":null,"timestamp":1775293033930,"callDuration":192855,"id":"69d0d271f3d7b3dad8c014f8","created_at":"2026-04-04T08:57:21.184000"},{"voiceQuality":4,"audioIssues":["CALL_PERFECT"],"environment":"INDOOR","comment":null,"carrier":"AIRTEL","networkGeneration":"WiFi","signalStrength":null,"latitude":null,"longitude":null,"timestamp":1775286056590,"callDuration":115927,"id":"69d0b72ff3d7b3dad8c014f7","created_at":"2026-04-04T07:01:03.362000"},{"voiceQuality":1,"audioIssues":["OTHER_COULD_NOT_HEAR_ME"],"environment":"INDOOR","comment":null,"carrier":"AIRTEL","networkGeneration":"WiFi","signalStrength":null,"latitude":null,"longitude":null,"timestamp":1775285908463,"callDuration":16530,"id":"69d0b69bf3d7b3dad8c014f6","created_at":"2026-04-04T06:58:35.672000"},{"voiceQuality":5,"audioIssues":["CALL_PERFECT"],"environment":"INDOOR","comment":null,"carrier":"Vi India","networkGeneration":"LTE","signalStrength":null,"latitude":null,"longitude":null,"timestamp":1775240887994,"callDuration":1933366,"id":"69d006bdf3d7b3dad8c014f5","created_at":"2026-04-03T18:28:13.064000"},{"voiceQuality":5,"audioIssues":null,"environment":"INDOOR","comment":null,"carrier":"AIRTEL","networkGeneration":"LTE","signalStrength":null,"latitude":null,"longitude":null,"timestamp":1775236207881,"callDuration":381599,"id":"69cff476f3d7b3dad8c014f4","created_at":"2026-04-03T17:10:14.112000"},{"voiceQuality":5,"audioIssues":["CALL_PERFECT"],"environment":"INDOOR","comment":null,"carrier":"AIRTEL","networkGeneration":"LTE","signalStrength":null,"latitude":null,"longitude":null,"timestamp":1775235780015,"callDuration":625077,"id":"69cff2c8f3d7b3dad8c014f3","created_at":"2026-04-03T17:03:04.569000"},{"voiceQuality":null,"audioIssues":null,"environment":null,"comment":null,"carrier":"Vi India","networkGeneration":"WiFi","signalStrength":null,"latitude":null,"longitude":null,"timestamp":1775235013579,"callDuration":933573,"id":"69cfefc6f3d7b3dad8c014f2","created_at":"2026-04-03T16:50:14.204000"},{"voiceQuality":5,"audioIssues":["CALL_PERFECT"],"environment":"INDOOR","comment":null,"carrier":"AIRTEL","networkGeneration":"WiFi","signalStrength":null,"latitude":null,"longitude":null,"timestamp":1775233479572,"callDuration":78199,"id":"69cfe9cbf3d7b3dad8c014f1","created_at":"2026-04-03T16:24:43.657000"},{"voiceQuality":5,"audioIssues":["CALL_PERFECT"],"environment":"INDOOR","comment":null,"carrier":"AIRTEL","networkGeneration":"WiFi","signalStrength":null,"latitude":null,"longitude":null,"timestamp":1775232075357,"callDuration":1547970,"id":"69cfe452f3d7b3dad8c014f0","created_at":"2026-04-03T16:01:22.895000"},{"voiceQuality":5,"audioIssues":["CALL_PERFECT"],"environment":"OUTDOOR","comment":null,"carrier":"AIRTEL","networkGeneration":"WiFi","signalStrength":null,"latitude":null,"longitude":null,"timestamp":1775230513638,"callDuration":1001262,"id":"69cfde36f3d7b3dad8c014ef","created_at":"2026-04-03T15:35:18.093000"},{"voiceQuality":5,"audioIssues":["CALL_PERFECT"],"environment":"INDOOR","comment":null,"carrier":"AIRTEL","networkGeneration":"LTE","signalStrength":null,"latitude":null,"longitude":null,"timestamp":1775229120359,"callDuration":41379,"id":"69cfd8c5f3d7b3dad8c014ee","created_at":"2026-04-03T15:12:05.214000"},{"voiceQuality":5,"audioIssues":["CALL_PERFECT"],"environment":"INDOOR","comment":null,"carrier":"AIRTEL","networkGeneration":"LTE","signalStrength":null,"latitude":null,"longitude":null,"timestamp":1775228009308,"callDuration":81894,"id":"69cfd720f3d7b3dad8c014ed","created_at":"2026-04-03T15:05:04.744000"},{"voiceQuality":4,"audioIssues":null,"environment":"INDOOR","comment":null,"carrier":"AIRTEL","networkGeneration":"LTE","signalStrength":null,"latitude":null,"longitude":null,"timestamp":1775223444263,"callDuration":11943,"id":"69cfc29ff3d7b3dad8c014ec","created_at":"2026-04-03T13:37:35.614000"},{"voiceQuality":5,"audioIssues":["CALL_PERFECT"],"environment":"INDOOR","comment":null,"carrier":"AIRTEL","networkGeneration":"LTE","signalStrength":null,"latitude":null,"longitude":null,"timestamp":1775216195257,"callDuration":12668,"id":"69cfb7cbf3d7b3dad8c014eb","created_at":"2026-04-03T12:51:23.115000"},{"voiceQuality":null,"audioIssues":null,"environment":null,"comment":null,"carrier":"Vi India","networkGeneration":"WiFi","signalStrength":null,"latitude":null,"longitude":null,"timestamp":1775212198420,"callDuration":35885,"id":"69cf96a9f3d7b3dad8c014ea","created_at":"2026-04-03T10:30:01.468000"},{"voiceQuality":null,"audioIssues":null,"environment":null,"comment":null,"carrier":"Vi India","networkGeneration":"WiFi","signalStrength":null,"latitude":null,"longitude":null,"timestamp":1775206055698,"callDuration":1208409,"id":"69cf7eb1f3d7b3dad8c014e9","created_at":"2026-04-03T08:47:45.742000"},{"voiceQuality":5,"audioIssues":["CALL_PERFECT"],"environment":"INDOOR","comment":null,"carrier":"AIRTEL","networkGeneration":"LTE","signalStrength":null,"latitude":null,"longitude":null,"timestamp":1775204875959,"callDuration":88988,"id":"69cf7a12f3d7b3dad8c014e8","created_at":"2026-04-03T08:28:02.023000"},{"voiceQuality":3,"audioIssues":null,"environment":"INDOOR","comment":null,"carrier":"AIRTEL","networkGeneration":"WiFi","signalStrength":null,"latitude":null,"longitude":null,"timestamp":1775195134357,"callDuration":17748,"id":"69cf5409f3d7b3dad8c014e7","created_at":"2026-04-03T05:45:45.517000"},{"voiceQuality":5,"audioIssues":["CALL_PERFECT"],"environment":"INDOOR","comment":null,"carrier":"AIRTEL","networkGeneration":"WiFi","signalStrength":null,"latitude":null,"longitude":null,"timestamp":1775193957121,"callDuration":50588,"id":"69cf4f68f3d7b3dad8c014e6","created_at":"2026-04-03T05:26:00.937000"},{"voiceQuality":5,"audioIssues":["CALL_PERFECT"],"environment":"INDOOR","comment":null,"carrier":"AIRTEL","networkGeneration":"WiFi","signalStrength":null,"latitude":null,"longitude":null,"timestamp":1775193617775,"callDuration":122896,"id":"69cf4e15f3d7b3dad8c014e5","created_at":"2026-04-03T05:20:21.210000"},{"voiceQuality":null,"audioIssues":null,"environment":null,"comment":null,"carrier":"","networkGeneration":"LTE","signalStrength":null,"latitude":null,"longitude":null,"timestamp":1775187787695,"callDuration":34224,"id":"69cf3752f3d7b3dad8c014e4","created_at":"2026-04-03T03:43:14.675000"},{"voiceQuality":null,"audioIssues":null,"environment":null,"comment":null,"carrier":"","networkGeneration":"LTE","signalStrength":null,"latitude":null,"longitude":null,"timestamp":1775158945775,"callDuration":11374,"id":"69cec6c7f3d7b3dad8c014e3","created_at":"2026-04-02T19:43:03.137000"},{"voiceQuality":null,"audioIssues":null,"environment":null,"comment":null,"carrier":"","networkGeneration":"LTE","signalStrength":null,"latitude":null,"longitude":null,"timestamp":1775158701384,"callDuration":81987,"id":"69cec5b1f3d7b3dad8c014e2","created_at":"2026-04-02T19:38:25.031000"},{"voiceQuality":5,"audioIssues":["CALL_PERFECT"],"environment":"INDOOR","comment":null,"carrier":"AIRTEL","networkGeneration":"WiFi","signalStrength":null,"latitude":null,"longitude":null,"timestamp":1775150176078,"callDuration":487763,"id":"69cea465f3d7b3dad8c014e1","created_at":"2026-04-02T17:16:21.195000"},{"voiceQuality":4,"audioIssues":["CALL_PERFECT"],"environment":"INDOOR","comment":null,"carrier":"AIRTEL","networkGeneration":"WiFi","signalStrength":null,"latitude":null,"longitude":null,"timestamp":1775149642296,"callDuration":907661,"id":"69cea251f3d7b3dad8c014e0","created_at":"2026-04-02T17:07:29.927000"},{"voiceQuality":5,"audioIssues":["CALL_PERFECT"],"environment":"INDOOR","comment":null,"carrier":"AIRTEL","networkGeneration":"LTE","signalStrength":null,"latitude":null,"longitude":null,"timestamp":1775145197425,"callDuration":633353,"id":"69ce90f4f3d7b3dad8c014df","created_at":"2026-04-02T15:53:24.953000"},{"voiceQuality":5,"audioIssues":["CALL_PERFECT"],"environment":"INDOOR","comment":null,"carrier":"AIRTEL","networkGeneration":"WiFi","signalStrength":null,"latitude":null,"longitude":null,"timestamp":1775144707583,"callDuration":28348,"id":"69ce8f08f3d7b3dad8c014de","created_at":"2026-04-02T15:45:12.473000"},{"voiceQuality":null,"audioIssues":null,"environment":null,"comment":null,"carrier":"","networkGeneration":"LTE","signalStrength":null,"latitude":null,"longitude":null,"timestamp":1775144167778,"callDuration":46483,"id":"69ce8d09f3d7b3dad8c014dd","created_at":"2026-04-02T15:36:41.650000"},{"voiceQuality":5,"audioIssues":["CALL_PERFECT"],"environment":"OUTDOOR","comment":null,"carrier":"AIRTEL","networkGeneration":"WiFi","signalStrength":null,"latitude":null,"longitude":null,"timestamp":1775143304617,"callDuration":1664,"id":"69ce898cf3d7b3dad8c014dc","created_at":"2026-04-02T15:21:48.339000"},{"voiceQuality":null,"audioIssues":null,"environment":null,"comment":null,"carrier":"AIRTEL","networkGeneration":"WiFi","signalStrength":null,"latitude":null,"longitude":null,"timestamp":1775143292090,"callDuration":54424,"id":"69ce897ef3d7b3dad8c014db","created_at":"2026-04-02T15:21:34.862000"},{"voiceQuality":null,"audioIssues":null,"environment":null,"comment":null,"carrier":"","networkGeneration":"LTE","signalStrength":null,"latitude":null,"longitude":null,"timestamp":1775135079254,"callDuration":94252,"id":"69ce696af3d7b3dad8c014da","created_at":"2026-04-02T13:04:42.128000"},{"voiceQuality":null,"audioIssues":null,"environment":null,"comment":null,"carrier":"","networkGeneration":"LTE","signalStrength":null,"latitude":null,"longitude":null,"timestamp":1775134980817,"callDuration":112506,"id":"69ce690cf3d7b3dad8c014d9","created_at":"2026-04-02T13:03:08.419000"},{"voiceQuality":null,"audioIssues":null,"environment":null,"comment":null,"carrier":"","networkGeneration":"LTE","signalStrength":null,"latitude":null,"longitude":null,"timestamp":1775134859264,"callDuration":124685,"id":"69ce688ff3d7b3dad8c014d8","created_at":"2026-04-02T13:01:03.394000"},{"voiceQuality":null,"audioIssues":null,"environment":null,"comment":null,"carrier":"","networkGeneration":"LTE","signalStrength":null,"latitude":null,"longitude":null,"timestamp":1775134482005,"callDuration":43288,"id":"69ce6715f3d7b3dad8c014d7","created_at":"2026-04-02T12:54:45.250000"},{"voiceQuality":null,"audioIssues":null,"environment":null,"comment":null,"carrier":"","networkGeneration":"LTE","signalStrength":null,"latitude":null,"longitude":null,"timestamp":1775132977049,"callDuration":174087,"id":"69ce6134f3d7b3dad8c014d6","created_at":"2026-04-02T12:29:40.732000"},{"voiceQuality":4,"audioIssues":["COULD_NOT_HEAR_OTHER"],"environment":"INDOOR","comment":null,"carrier":"","networkGeneration":"LTE","signalStrength":null,"latitude":null,"longitude":null,"timestamp":1775132784924,"callDuration":103398,"id":"69ce6080f3d7b3dad8c014d5","created_at":"2026-04-02T12:26:40.592000"},{"voiceQuality":5,"audioIssues":["CALL_PERFECT"],"environment":"INDOOR","comment":null,"carrier":"AIRTEL","networkGeneration":"WiFi","signalStrength":null,"latitude":null,"longitude":null,"timestamp":1775130823624,"callDuration":28074,"id":"69ce58cef3d7b3dad8c014d4","created_at":"2026-04-02T11:53:50.063000"},{"voiceQuality":5,"audioIssues":["CALL_PERFECT"],"environment":null,"comment":null,"carrier":"Vi India","networkGeneration":"WiFi","signalStrength":null,"latitude":null,"longitude":null,"timestamp":1775130826067,"callDuration":48054,"id":"69ce58ccf3d7b3dad8c014d3","created_at":"2026-04-02T11:53:48.617000"},{"voiceQuality":null,"audioIssues":null,"environment":null,"comment":null,"carrier":"","networkGeneration":"LTE","signalStrength":null,"latitude":null,"longitude":null,"timestamp":1775126142838,"callDuration":341273,"id":"69ce4683f3d7b3dad8c014d2","created_at":"2026-04-02T10:35:47.226000"},{"voiceQuality":5,"audioIssues":["CALL_PERFECT"],"environment":"OUTDOOR","comment":null,"carrier":"AIRTEL","networkGeneration":"WiFi","signalStrength":null,"latitude":null,"longitude":null,"timestamp":1775123981313,"callDuration":2456,"id":"69ce3e14f3d7b3dad8c014d1","created_at":"2026-04-02T09:59:48.493000"},{"voiceQuality":2,"audioIssues":["CALL_DROPPED"],"environment":"INDOOR","comment":null,"carrier":"AIRTEL","networkGeneration":"WiFi","signalStrength":null,"latitude":null,"longitude":null,"timestamp":1775121545418,"callDuration":917,"id":"69ce348ff3d7b3dad8c014d0","created_at":"2026-04-02T09:19:11.477000"},{"voiceQuality":null,"audioIssues":["CALL_PERFECT"],"environment":null,"comment":null,"carrier":"","networkGeneration":"WiFi","signalStrength":null,"latitude":null,"longitude":null,"timestamp":1775115241407,"callDuration":33553,"id":"69ce1beef3d7b3dad8c014cf","created_at":"2026-04-02T07:34:06.750000"},{"voiceQuality":5,"audioIssues":["CALL_DROPPED"],"environment":"INDOOR","comment":null,"carrier":"","networkGeneration":"WiFi","signalStrength":null,"latitude":null,"longitude":null,"timestamp":1775113931846,"callDuration":2668,"id":"69ce16e1f3d7b3dad8c014ce","created_at":"2026-04-02T07:12:33.164000"},{"voiceQuality":5,"audioIssues":["CALL_PERFECT"],"environment":null,"comment":null,"carrier":"Vi India","networkGeneration":"LTE","signalStrength":null,"latitude":null,"longitude":null,"timestamp":1775113653967,"callDuration":15476,"id":"69ce15b9f3d7b3dad8c014cd","created_at":"2026-04-02T07:07:37.487000"},{"voiceQuality":5,"audioIssues":["CALL_PERFECT"],"environment":"INDOOR","comment":null,"carrier":"AIRTEL","networkGeneration":"WiFi","signalStrength":null,"latitude":null,"longitude":null,"timestamp":1775106828795,"callDuration":7785,"id":"69cdfb3ff3d7b3dad8c014cc","created_at":"2026-04-02T05:14:39.299000"},{"voiceQuality":4,"audioIssues":null,"environment":"INDOOR","comment":null,"carrier":"AIRTEL","networkGeneration":"WiFi","signalStrength":null,"latitude":null,"longitude":null,"timestamp":1775105190603,"callDuration":1256,"id":"69cdf4b7f3d7b3dad8c014cb","created_at":"2026-04-02T04:46:47.688000"},{"voiceQuality":5,"audioIssues":["CALL_PERFECT"],"environment":"INDOOR","comment":null,"carrier":"AIRTEL","networkGeneration":"WiFi","signalStrength":null,"latitude":null,"longitude":null,"timestamp":1775066629246,"callDuration":175356,"id":"69cd5e11f3d7b3dad8c014ca","created_at":"2026-04-01T18:04:01.231000"},{"voiceQuality":null,"audioIssues":null,"environment":null,"comment":null,"carrier":"Vi India","networkGeneration":"LTE","signalStrength":null,"latitude":null,"longitude":null,"timestamp":1775066630109,"callDuration":159379,"id":"69cd5e0bf3d7b3dad8c014c9","created_at":"2026-04-01T18:03:55.301000"},{"voiceQuality":4,"audioIssues":["CALL_PERFECT"],"environment":"INDOOR","comment":null,"carrier":"AIRTEL","networkGeneration":"WiFi","signalStrength":null,"latitude":null,"longitude":null,"timestamp":1775065674089,"callDuration":1868,"id":"69cd5a4e94db0ea53da37530","created_at":"2026-04-01T17:47:58.566000"},{"voiceQuality":null,"audioIssues":null,"environment":null,"comment":null,"carrier":"AIRTEL","networkGeneration":"WiFi","signalStrength":null,"latitude":null,"longitude":null,"timestamp":1775065280585,"callDuration":3097,"id":"69cd58c212f01a675481b57a","created_at":"2026-04-01T17:41:22.183000"},{"voiceQuality":3,"audioIssues":["CALL_PERFECT"],"environment":"OUTDOOR","comment":null,"carrier":"AIRTEL","networkGeneration":"WiFi","signalStrength":null,"latitude":null,"longitude":null,"timestamp":1775065266171,"callDuration":3695,"id":"69cd58b712f01a675481b579","created_at":"2026-04-01T17:41:11.242000"},{"voiceQuality":null,"audioIssues":null,"environment":null,"comment":null,"carrier":"AIRTEL","networkGeneration":"WiFi","signalStrength":null,"latitude":null,"longitude":null,"timestamp":1775065141089,"callDuration":63967,"id":"69cd583a12f01a675481b578","created_at":"2026-04-01T17:39:06.676000"}]